crossfire/__init__.py
crossfire/clients/__init__.py
crossfire/clients/occurrences.py
crossfire/errors.py
crossfire/logger.py
crossfire/parser.py
crossfire-1.1.1.dist-info/WHEEL
crossfire-1.1.1.dist-info/METADATA
crossfire-1.1.1.dist-info/RECORD
