Metadata-Version: 2.1
Name: crossfire
Version: 1.1.1
Summary: crossfire: Download spatial data sets from crossfire project
Home-page: https://fogocruzado.org.br/
Author: Felipe Barros
Author-email: felipe.b4rros@gmail.com
Requires-Python: >=3.9,<3.13
Classifier: Intended Audience :: Developers
Classifier: Intended Audience :: Education
Classifier: Intended Audience :: Science/Research
Classifier: Programming Language :: Python
Classifier: Programming Language :: Python :: 3
Classifier: Programming Language :: Python :: 3.9
Classifier: Programming Language :: Python :: 3.10
Classifier: Programming Language :: Python :: 3.11
Classifier: Topic :: Scientific/Engineering :: GIS
Classifier: Topic :: Scientific/Engineering :: Visualization
Provides-Extra: df
Provides-Extra: geodf
Requires-Dist: geopandas (>=0.13.2,<0.14.0) ; extra == "geodf"
Requires-Dist: httpx (>=0.25.0,<0.26.0)
Requires-Dist: nest-asyncio (>=1.6.0,<2.0.0)
Requires-Dist: pandas (>=2.1.1,<3.0.0) ; extra == "df" or extra == "geodf"
Requires-Dist: python-decouple (>=3.5,<4.0)
Requires-Dist: tqdm (>=4.66.1,<5.0.0)
Project-URL: Repository, https://github.com/felipesbarros/crossfire
